decaptcha/__init__.py
decaptcha/_version.py
decaptcha/base.py
decaptcha/black3x3.png
decaptcha/black4x4.png
decaptcha/bluecheck.png
decaptcha/fsm.py
decaptcha/greencheck.png
decaptcha/humanclick.py
decaptcha/imgai.py
decaptcha/imnotarobot.png
decaptcha/next.png
decaptcha/notarobot.py
decaptcha/ocr.py
decaptcha/puzzle_frame.png
decaptcha/skip.png
decaptcha/verify.png
decaptcha/version.py
decaptcha-1.0.2.dist-info/LICENSE
decaptcha-1.0.2.dist-info/METADATA
decaptcha-1.0.2.dist-info/WHEEL
decaptcha-1.0.2.dist-info/top_level.txt
decaptcha-1.0.2.dist-info/RECORD
