Metadata-Version: 2.1
Name: decaptcha
Version: 1.0.2
Summary: A GUI automation Python module for solving Google reCAPTCHA v2
Home-page: https://github.com/balanceofprobability/decaptcha
Author: John Harrison
Author-email: balanceofprobability@gmail.com
License: MIT license
Keywords: decaptcha
Platform: UNKNOWN
Classifier: Development Status :: 3 - Alpha
Classifier: Intended Audience :: Developers
Classifier: License :: OSI Approved :: MIT License
Classifier: Natural Language :: English
Classifier: Programming Language :: Python :: 3.6
Requires-Dist: imageai
Requires-Dist: keras
Requires-Dist: opencv-python
Requires-Dist: pillow (>=6.2.0)
Requires-Dist: pyautogui
Requires-Dist: pyscreenshot
Requires-Dist: tensorflow (==1.15.2)
Requires-Dist: tesserocr
